{
  "entrypoint": "index.html",
  "shell": "src/my-app.js",
  "sources": [
    "images/**/*"
  ],
  "extraDependencies": [
    "manifest.json",
    "node_modules/@webcomponents/webcomponentsjs/*.js",
    "!node_modules/@webcomponents/webcomponentsjs/gulpfile.js",
    "node_modules/@webcomponents/webcomponentsjs/bundles/*.js"
  ],
  "builds": [
    {
      "name": "es6-bundled",
      "browserCapabilities": [
        "es2017"
      ],
      "js": {
        "minify": false,
        "transformModulesToAmd": false
      },
      "css": {
        "minify": false
      },
      "html": {
        "minify": false
      },
      "bundle": false,
      "addServiceWorker": false
    }
  ],
  "moduleResolution": "node",
  "npm": true,
  "lint": {
    "rules": [
      "polymer-3"
    ]
  }
}
